demoproject/__init__.py
demoproject/asgi.py
demoproject/settings.py
demoproject/urls.py
demoproject/wsgi.py
django_jtable/__init__.py
django_jtable/admin.py
django_jtable/apps.py
django_jtable/models.py
django_jtable/tests.py
django_jtable/viewbuilder.py
django_jtable-0.1.1.dist-info/licenses/LICENSE
student/__init__.py
student/admin.py
student/apps.py
student/models.py
student/tests.py
student/urls.py
student/views.py
django_jtable-0.1.1.dist-info/METADATA
django_jtable-0.1.1.dist-info/WHEEL
django_jtable-0.1.1.dist-info/top_level.txt
django_jtable-0.1.1.dist-info/RECORD
