Metadata-Version: 2.4
Name: django-jtable
Version: 0.1.1
Summary: Django + jTable integration
Author: Ezhil Language Foundation
License: MIT
Project-URL: Homepage, https://github.com/ezhil-Language-Foundation/django-jtable
Project-URL: Source, https://github.com/ezhil-Language-Foundation/django-jtable
Classifier: Programming Language :: Python :: 3
Classifier: Framework :: Django
Classifier: License :: OSI Approved :: MIT License
Classifier: Operating System :: OS Independent
Requires-Python: >=3.8
License-File: LICENSE
Requires-Dist: Django>=3.2
Requires-Dist: django-cors-headers>=3.13
Dynamic: license-file
